{
  "NavbarMenus": [
    {
      "name": "主页",
      "icon": "fa fa-home",
      "url": "/Index"
    },
    {
      "name": "订单系统",
      "icon": "fa fa-pencil-square-o",
      "url": 1,
      "children": [
        {
          "name": "旧版",
          "icon": "fa fa-circle-o",
          "url": "",
          "children": [
            {
              "name": "发货单",
              "icon": "fa fa-circle-o",
              "url": "/OrderManagement/Old/DeliveryOrder/Index"
            }
          ]
        }
      ]
    },
    {
      "name": "采购系统",
      "icon": "fa fa-500px",
      "url": 2
    },
    {
      "name": "管理员菜单",
      "icon": "fa fa-cog",
      "url": 3,
      "children": [
        {
          "name": "菜单管理",
          "icon": "fa fa-circle-o",
          "url": "/MenuManagement/Index"
        },
        {
          "name": "用户管理",
          "icon": "fa fa-circle-o",
          "url": "/User/Index"
        },
        {
          "name": "角色管理",
          "icon": "fa fa-circle-o",
          "url": "/Role/Index"
        },
        {
          "name": "权限管理",
          "icon": "fa fa-circle-o",
          "url": "/Permission/Index"
        }
      ]
    }
  ]
}